{
	"configurations" : 
	[
		{
			"directories" : 
			[
				{
					"build" : ".",
					"jsonFile" : "directory-.-Debug-d0094a50bb2071803777.json",
					"minimumCMakeVersion" : 
					{
						"string" : "3.29"
					},
					"projectIndex" : 0,
					"source" : ".",
					"targetIndexes" : 
					[
						0
					]
				}
			],
			"name" : "Debug",
			"projects" : 
			[
				{
					"directoryIndexes" : 
					[
						0
					],
					"name" : "lab7C",
					"targetIndexes" : 
					[
						0
					]
				}
			],
			"targets" : 
			[
				{
					"directoryIndex" : 0,
					"id" : "lab7C::@6890427a1f51a3e7e1df",
					"jsonFile" : "target-lab7C-Debug-c3ecd1731c10a6c9a81f.json",
					"name" : "lab7C",
					"projectIndex" : 0
				}
			]
		}
	],
	"kind" : "codemodel",
	"paths" : 
	{
		"build" : "E:/CST HOMEWORK/MAIN_PC_HW/lab7C/cmake-build-debug",
		"source" : "E:/CST HOMEWORK/MAIN_PC_HW/lab7C"
	},
	"version" : 
	{
		"major" : 2,
		"minor" : 7
	}
}
